aliyun_oss2_storage/__init__.py
aliyun_oss2_storage/backends.py
django3_aliyun_oss2_storage-0.1.3.dist-info/LICENSE
django3_aliyun_oss2_storage-0.1.3.dist-info/METADATA
django3_aliyun_oss2_storage-0.1.3.dist-info/WHEEL
django3_aliyun_oss2_storage-0.1.3.dist-info/top_level.txt
django3_aliyun_oss2_storage-0.1.3.dist-info/RECORD
